{
  "formatVersion": 1,
  "database": {
    "version": 1,
    "identityHash": "73b6e909a25e6c6207f227632e519ade",
    "entities": [
      {
        "tableName": "songs",
        "createSql": "CREATE TABLE IF NOT EXISTS `${TABLE_NAME}` (`id` INTEGER NOT NULL, `title` TEXT NOT NULL, `artist` TEXT NOT NULL, `album` TEXT NOT NULL, `album_id` INTEGER NOT NULL, `artist_id` INTEGER NOT NULL, `uri` TEXT NOT NULL, `duration` INTEGER NOT NULL, `size` INTEGER NOT NULL, `path` TEXT NOT NULL, `art_uri` TEXT, `track_number` INTEGER NOT NULL, `year` INTEGER NOT NULL, `genre` TEXT NOT NULL, `date_added` INTEGER NOT NULL, `date_modified` INTEGER NOT NULL, PRIMARY KEY(`id`))",
        "fields": [
          {
            "fieldPath": "id",
            "columnName": "id",
            "affinity": "INTEGER",
            "notNull": true
          },
          {
            "fieldPath": "title",
            "columnName": "title",
            "affinity": "TEXT",
            "notNull": true
          },
          {
            "fieldPath": "artist",
            "columnName": "artist",
            "affinity": "TEXT",
            "notNull": true
          },
          {
            "fieldPath": "album",
            "columnName": "album",
            "affinity": "TEXT",
            "notNull": true
          },
          {
            "fieldPath": "albumId",
            "columnName": "album_id",
            "affinity": "INTEGER",
            "notNull": true
          },
          {
            "fieldPath": "artistId",
            "columnName": "artist_id",
            "affinity": "INTEGER",
            "notNull": true
          },
          {
            "fieldPath": "uri",
            "columnName": "uri",
            "affinity": "TEXT",
            "notNull": true
          },
          {
            "fieldPath": "duration",
            "columnName": "duration",
            "affinity": "INTEGER",
            "notNull": true
          },
          {
            "fieldPath": "size",
            "columnName": "size",
            "affinity": "INTEGER",
            "notNull": true
          },
          {
            "fieldPath": "path",
            "columnName": "path",
            "affinity": "TEXT",
            "notNull": true
          },
          {
            "fieldPath": "artUri",
            "columnName": "art_uri",
            "affinity": "TEXT",
            "notNull": false
          },
          {
            "fieldPath": "trackNumber",
            "columnName": "track_number",
            "affinity": "INTEGER",
            "notNull": true
          },
          {
            "fieldPath": "year",
            "columnName": "year",
            "affinity": "INTEGER",
            "notNull": true
          },
          {
            "fieldPath": "genre",
            "columnName": "genre",
            "affinity": "TEXT",
            "notNull": true
          },
          {
            "fieldPath": "dateAdded",
            "columnName": "date_added",
            "affinity": "INTEGER",
            "notNull": true
          },
          {
            "fieldPath": "dateModified",
            "columnName": "date_modified",
            "affinity": "INTEGER",
            "notNull": true
          }
        ],
        "primaryKey": {
          "autoGenerate": false,
          "columnNames": [
            "id"
          ]
        },
        "indices": [],
        "foreignKeys": []
      },
      {
        "tableName": "playlists",
        "createSql": "CREATE TABLE IF NOT EXISTS `${TABLE_NAME}` (`id` INTEGER PRIMARY KEY AUTOINCREMENT NOT NULL, `name` TEXT NOT NULL, `created_at` INTEGER NOT NULL, `modified_at` INTEGER NOT NULL)",
        "fields": [
          {
            "fieldPath": "id",
            "columnName": "id",
            "affinity": "INTEGER",
            "notNull": true
          },
          {
            "fieldPath": "name",
            "columnName": "name",
            "affinity": "TEXT",
            "notNull": true
          },
          {
            "fieldPath": "createdAt",
            "columnName": "created_at",
            "affinity": "INTEGER",
            "notNull": true
          },
          {
            "fieldPath": "modifiedAt",
            "columnName": "modified_at",
            "affinity": "INTEGER",
            "notNull": true
          }
        ],
        "primaryKey": {
          "autoGenerate": true,
          "columnNames": [
            "id"
          ]
        },
        "indices": [],
        "foreignKeys": []
      },
      {
        "tableName": "playlist_song_cross_ref",
        "createSql": "CREATE TABLE IF NOT EXISTS `${TABLE_NAME}` (`playlist_id` INTEGER NOT NULL, `song_id` INTEGER NOT NULL, `sort_order` INTEGER NOT NULL, `added_at` INTEGER NOT NULL, PRIMARY KEY(`playlist_id`, `song_id`))",
        "fields": [
          {
            "fieldPath": "playlistId",
            "columnName": "playlist_id",
            "affinity": "INTEGER",
            "notNull": true
          },
          {
            "fieldPath": "songId",
            "columnName": "song_id",
            "affinity": "INTEGER",
            "notNull": true
          },
          {
            "fieldPath": "sortOrder",
            "columnName": "sort_order",
            "affinity": "INTEGER",
            "notNull": true
          },
          {
            "fieldPath": "addedAt",
            "columnName": "added_at",
            "affinity": "INTEGER",
            "notNull": true
          }
        ],
        "primaryKey": {
          "autoGenerate": false,
          "columnNames": [
            "playlist_id",
            "song_id"
          ]
        },
        "indices": [],
        "foreignKeys": []
      }
    ],
    "views": [],
    "setupQueries": [
      "CREATE TABLE IF NOT EXISTS room_master_table (id INTEGER PRIMARY KEY,identity_hash TEXT)",
      "INSERT OR REPLACE INTO room_master_table (id,identity_hash) VALUES(42, '73b6e909a25e6c6207f227632e519ade')"
    ]
  }
}